{
  "preproduction-script": {
    "id": "preproduction-script",
    "name": "Script",
    "group": "preproduction",
    "nodes": [
      {
        "id": "input-preproduction-script",
        "type": "input",
        "label": "Input",
        "position": {
          "x": 100.0,
          "y": 200.0
        },
        "isRunning": false,
        "isDeactivated": false,
        "supervised": false,
        "baseCodeTemplate": "default"
      },
      {
        "id": "output-preproduction-script",
        "type": "output",
        "label": "Output",
        "position": {
          "x": 920.0,
          "y": 196.0
        },
        "isRunning": false,
        "isDeactivated": false,
        "supervised": false,
        "connectedFrom": [],
        "baseCodeTemplate": "default"
      }
    ]
  },
  "preproduction-storyboard": {
    "id": "preproduction-storyboard",
    "name": "Storyboard",
    "group": "preproduction",
    "nodes": [
      {
        "id": "input-preproduction-storyboard",
        "type": "input",
        "label": "Input",
        "position": {
          "x": 100.0,
          "y": 200.0
        },
        "isRunning": false,
        "isDeactivated": false,
        "supervised": false,
        "baseCodeTemplate": "default"
      },
      {
        "id": "output-preproduction-storyboard",
        "type": "output",
        "label": "Output",
        "position": {
          "x": 700.0,
          "y": 200.0
        },
        "isRunning": false,
        "isDeactivated": false,
        "supervised": false,
        "connectedFrom": [],
        "baseCodeTemplate": "default"
      }
    ]
  },
  "preproduction-planning": {
    "id": "preproduction-planning",
    "name": "Planning",
    "group": "preproduction",
    "nodes": [
      {
        "id": "input-preproduction-planning",
        "type": "input",
        "label": "Input",
        "position": {
          "x": 100.0,
          "y": 200.0
        },
        "isRunning": false,
        "isDeactivated": false,
        "supervised": false,
        "baseCodeTemplate": "default"
      },
      {
        "id": "output-preproduction-planning",
        "type": "output",
        "label": "Output",
        "position": {
          "x": 700.0,
          "y": 200.0
        },
        "isRunning": false,
        "isDeactivated": false,
        "supervised": false,
        "connectedFrom": [],
        "baseCodeTemplate": "default"
      }
    ]
  },
  "postproduction-modeling": {
    "id": "postproduction-modeling",
    "name": "Modeling",
    "group": "postproduction",
    "nodes": [
      {
        "id": "input-postproduction-modeling",
        "type": "input",
        "label": "Input",
        "position": {
          "x": 100.0,
          "y": 200.0
        },
        "isRunning": false,
        "isDeactivated": false,
        "supervised": false,
        "baseCodeTemplate": "default"
      },
      {
        "id": "output-postproduction-modeling",
        "type": "output",
        "label": "Output",
        "position": {
          "x": 700.0,
          "y": 200.0
        },
        "isRunning": false,
        "isDeactivated": false,
        "supervised": false,
        "connectedFrom": [],
        "baseCodeTemplate": "default"
      }
    ]
  },
  "postproduction-rigging": {
    "id": "postproduction-rigging",
    "name": "Rigging",
    "group": "postproduction",
    "nodes": [
      {
        "id": "input-postproduction-rigging",
        "type": "input",
        "label": "Input",
        "position": {
          "x": 100.0,
          "y": 200.0
        },
        "isRunning": false,
        "isDeactivated": false,
        "supervised": false,
        "baseCodeTemplate": "default"
      },
      {
        "id": "output-postproduction-rigging",
        "type": "output",
        "label": "Output",
        "position": {
          "x": 700.0,
          "y": 200.0
        },
        "isRunning": false,
        "isDeactivated": false,
        "supervised": false,
        "connectedFrom": [],
        "baseCodeTemplate": "default"
      }
    ]
  },
  "postproduction-texture": {
    "id": "postproduction-texture",
    "name": "Texture",
    "group": "postproduction",
    "nodes": [
      {
        "id": "input-postproduction-texture",
        "type": "input",
        "label": "Input",
        "position": {
          "x": 100.0,
          "y": 200.0
        },
        "isRunning": false,
        "isDeactivated": false,
        "supervised": false,
        "baseCodeTemplate": "default"
      },
      {
        "id": "output-postproduction-texture",
        "type": "output",
        "label": "Output",
        "position": {
          "x": 700.0,
          "y": 200.0
        },
        "isRunning": false,
        "isDeactivated": false,
        "supervised": false,
        "connectedFrom": [],
        "baseCodeTemplate": "default"
      }
    ]
  },
  "postproduction-animation": {
    "id": "postproduction-animation",
    "name": "Animation",
    "group": "postproduction",
    "nodes": [
      {
        "id": "input-postproduction-animation",
        "type": "input",
        "label": "Input",
        "position": {
          "x": 100.0,
          "y": 200.0
        },
        "isRunning": false,
        "isDeactivated": false,
        "supervised": false,
        "baseCodeTemplate": "default"
      },
      {
        "id": "output-postproduction-animation",
        "type": "output",
        "label": "Output",
        "position": {
          "x": 700.0,
          "y": 200.0
        },
        "isRunning": false,
        "isDeactivated": false,
        "supervised": false,
        "connectedFrom": [],
        "baseCodeTemplate": "default"
      }
    ]
  },
  "postproduction-vfx": {
    "id": "postproduction-vfx",
    "name": "VFX",
    "group": "postproduction",
    "nodes": [
      {
        "id": "input-postproduction-vfx",
        "type": "input",
        "label": "Input",
        "position": {
          "x": 100.0,
          "y": 200.0
        },
        "isRunning": false,
        "isDeactivated": false,
        "supervised": false,
        "baseCodeTemplate": "default"
      },
      {
        "id": "output-postproduction-vfx",
        "type": "output",
        "label": "Output",
        "position": {
          "x": 700.0,
          "y": 200.0
        },
        "isRunning": false,
        "isDeactivated": false,
        "supervised": false,
        "connectedFrom": [],
        "baseCodeTemplate": "default"
      }
    ]
  },
  "postproduction-lighting-&-rendering": {
    "id": "postproduction-lighting-&-rendering",
    "name": "Lighting & Rendering",
    "group": "postproduction",
    "nodes": [
      {
        "id": "input-postproduction-lighting-&-rendering",
        "type": "input",
        "label": "Input",
        "position": {
          "x": 100.0,
          "y": 200.0
        },
        "isRunning": false,
        "isDeactivated": false,
        "supervised": false,
        "baseCodeTemplate": "default"
      },
      {
        "id": "output-postproduction-lighting-&-rendering",
        "type": "output",
        "label": "Output",
        "position": {
          "x": 700.0,
          "y": 200.0
        },
        "isRunning": false,
        "isDeactivated": false,
        "supervised": false,
        "connectedFrom": [],
        "baseCodeTemplate": "default"
      }
    ]
  },
  "postproduction-sound-design": {
    "id": "postproduction-sound-design",
    "name": "Sound Design",
    "group": "postproduction",
    "nodes": [
      {
        "id": "input-postproduction-sound-design",
        "type": "input",
        "label": "Input",
        "position": {
          "x": 100.0,
          "y": 200.0
        },
        "isRunning": false,
        "isDeactivated": false,
        "supervised": false,
        "baseCodeTemplate": "default"
      },
      {
        "id": "output-postproduction-sound-design",
        "type": "output",
        "label": "Output",
        "position": {
          "x": 700.0,
          "y": 200.0
        },
        "isRunning": false,
        "isDeactivated": false,
        "supervised": false,
        "connectedFrom": [],
        "baseCodeTemplate": "default"
      }
    ]
  },
  "postproduction-compositing": {
    "id": "postproduction-compositing",
    "name": "Compositing",
    "group": "postproduction",
    "nodes": [
      {
        "id": "input-postproduction-compositing",
        "type": "input",
        "label": "Input",
        "position": {
          "x": 100.0,
          "y": 200.0
        },
        "isRunning": false,
        "isDeactivated": false,
        "supervised": false,
        "baseCodeTemplate": "default"
      },
      {
        "id": "output-postproduction-compositing",
        "type": "output",
        "label": "Output",
        "position": {
          "x": 700.0,
          "y": 200.0
        },
        "isRunning": false,
        "isDeactivated": false,
        "supervised": false,
        "connectedFrom": [],
        "baseCodeTemplate": "default"
      }
    ]
  },
  "director-direction": {
    "id": "director-direction",
    "name": "Direction",
    "group": "director",
    "nodes": [
      {
        "id": "input-director-direction",
        "type": "input",
        "label": "Input",
        "position": {
          "x": 100.0,
          "y": 200.0
        },
        "isRunning": false,
        "isDeactivated": false,
        "supervised": false,
        "baseCodeTemplate": "default"
      },
      {
        "id": "output-director-direction",
        "type": "output",
        "label": "Output",
        "position": {
          "x": 700.0,
          "y": 200.0
        },
        "isRunning": false,
        "isDeactivated": false,
        "supervised": false,
        "connectedFrom": [],
        "baseCodeTemplate": "default"
      }
    ]
  },
  "director-review": {
    "id": "director-review",
    "name": "Review",
    "group": "director",
    "nodes": [
      {
        "id": "input-director-review",
        "type": "input",
        "label": "Input",
        "position": {
          "x": 100.0,
          "y": 200.0
        },
        "isRunning": false,
        "isDeactivated": false,
        "supervised": false,
        "baseCodeTemplate": "default"
      },
      {
        "id": "output-director-review",
        "type": "output",
        "label": "Output",
        "position": {
          "x": 700.0,
          "y": 200.0
        },
        "isRunning": false,
        "isDeactivated": false,
        "supervised": false,
        "connectedFrom": [],
        "baseCodeTemplate": "default"
      }
    ]
  }
}